{
  "type": "FeatureCollection",
  "features": [
    {
      "type": "Feature",
      "properties": {
        "name": "Cascata Angolares",
        "country": "São Tomé and Príncipe",
        "country_code": "st",
        "county": "Lembá",
        "city": "Ponta Figo",
        "hamlet": "Cadão",
        "municipality": "Neves",
        "street": "EN1",
        "iso3166_2": "ST-04",
        "lon": 6.5538617,
        "lat": 0.2971687,
        "formatted": "Cascata Angolares, EN1, Ponta Figo, São Tomé and Príncipe",
        "address_line1": "Cascata Angolares",
        "address_line2": "EN1, Ponta Figo, São Tomé and Príncipe",
        "categories": [
          "tourism",
          "tourism.attraction"
        ],
        "details": [
          "details"
        ],
        "datasource": {
          "sourcename": "openstreetmap",
          "attribution": "© OpenStreetMap contributors",
          "license": "Open Database License",
          "url": "https://www.openstreetmap.org/copyright",
          "raw": {
            "name": "Cascata Angolares",
            "osm_id": 11992120794,
            "tourism": "attraction",
            "osm_type": "n",
            "opening_hours": "24/7"
          }
        },
        "opening_hours": "24/7",
        "place_id": "512107808527371a4059a5cef0ddcf04d33ff00103f901da3dc9ca020000009203114361736361746120416e676f6c61726573"
      },
      "geometry": {
        "type": "Point",
        "coordinates": [
          6.5538617,
          0.2971686999692145
        ]
      }
    },
    {
      "type": "Feature",
      "properties": {
        "name": "Jardim Botânico",
        "country": "São Tomé and Príncipe",
        "country_code": "st",
        "county": "Mé-Zóchi",
        "city": "Monte Café",
        "hamlet": "Aldeamenta de Monta Café",
        "municipality": "Trindade",
        "street": "EN 3",
        "iso3166_2": "ST-06",
        "lon": 6.6121603,
        "lat": 0.2890468,
        "formatted": "Botanical Garden, EN 3, Monte Café, São Tomé and Príncipe",
        "address_line1": "Botanical Garden",
        "address_line2": "EN 3, Monte Café, São Tomé and Príncipe",
        "categories": [
          "tourism",
          "tourism.attraction"
        ],
        "details": [
          "details"
        ],
        "datasource": {
          "sourcename": "openstreetmap",
          "attribution": "© OpenStreetMap contributors",
          "license": "Open Database License",
          "url": "https://www.openstreetmap.org/copyright",
          "raw": {
            "name": "Jardim Botânico",
            "osm_id": 938537793,
            "name:de": "Botanischer Garten",
            "name:en": "Botanical Garden",
            "name:es": "Jardín Botánico",
            "tourism": "attraction",
            "osm_type": "n"
          }
        },
        "name_international": {
          "de": "Botanischer Garten",
          "en": "Botanical Garden",
          "es": "Jardín Botánico"
        },
        "place_id": "5162a35126da721a4059a8a13826be7fd23ff00103f90141f3f037000000009203104a617264696d20426f74c3a26e69636f"
      },
      "geometry": {
        "type": "Point",
        "coordinates": [
          6.612160300000001,
          0.2890467999700612
        ]
      }
    },
    {
      "type": "Feature",
      "properties": {
        "name": "Roça Agostinho Neto ( Roça de Cinco mil)",
        "country": "São Tomé and Príncipe",
        "country_code": "st",
        "county": "Lobata",
        "city": "Guadalupe",
        "hamlet": "Quilombo Guadalupe",
        "municipality": "Guadalupe",
        "street": "EN1",
        "iso3166_2": "ST-05",
        "lon": 6.6449742,
        "lat": 0.3686563,
        "formatted": "Roça Agostinho Neto ( Roça de Cinco mil), EN1, Guadalupe, São Tomé and Príncipe",
        "address_line1": "Roça Agostinho Neto ( Roça de Cinco mil)",
        "address_line2": "EN1, Guadalupe, São Tomé and Príncipe",
        "categories": [
          "tourism",
          "tourism.attraction",
          "tourism.attraction.viewpoint"
        ],
        "details": [],
        "datasource": {
          "sourcename": "openstreetmap",
          "attribution": "© OpenStreetMap contributors",
          "license": "Open Database License",
          "url": "https://www.openstreetmap.org/copyright",
          "raw": {
            "name": "Roça Agostinho Neto ( Roça de Cinco mil)",
            "osm_id": 1600956613,
            "tourism": "viewpoint",
            "osm_type": "n"
          }
        },
        "place_id": "51170edf1d74941a40595632f3971098d73ff00103f901c5a86c5f0000000092032a526fc3a7612041676f7374696e686f204e65746f202820526fc3a7612064652043696e636f206d696c29"
      },
      "geometry": {
        "type": "Point",
        "coordinates": [
          6.644974199999999,
          0.36865629996171856
        ]
      }
    },
    {
      "type": "Feature",
      "properties": {
        "name": "Cascata de São Nicolau",
        "country": "São Tomé and Príncipe",
        "country_code": "st",
        "county": "Mé-Zóchi",
        "city": "Monte Café",
        "hamlet": "Aldeamenta de Monta Café",
        "municipality": "Trindade",
        "street": "EN 3",
        "iso3166_2": "ST-06",
        "lon": 6.625283,
        "lat": 0.286066,
        "formatted": "Cascata de São Nicolau, EN 3, Monte Café, São Tomé and Príncipe",
        "address_line1": "Cascata de São Nicolau",
        "address_line2": "EN 3, Monte Café, São Tomé and Príncipe",
        "categories": [
          "tourism",
          "tourism.attraction",
          "tourism.attraction.viewpoint"
        ],
        "details": [],
        "datasource": {
          "sourcename": "openstreetmap",
          "attribution": "© OpenStreetMap contributors",
          "license": "Open Database License",
          "url": "https://www.openstreetmap.org/copyright",
          "raw": {
            "name": "Cascata de São Nicolau",
            "osm_id": 1860567160,
            "tourism": "viewpoint",
            "osm_type": "n",
            "waterway": "waterfall"
          }
        },
        "place_id": "51a4face2f4a801a405986b297c4e74ed23ff00103f9017800e66e00000000920317436173636174612064652053c3a36f204e69636f6c6175"
      },
      "geometry": {
        "type": "Point",
        "coordinates": [
          6.625283,
          0.28606599997036886
        ]
      }
    },
    {
      "type": "Feature",
      "properties": {
        "name": "Lagoa Azul",
        "country": "São Tomé and Príncipe",
        "country_code": "st",
        "county": "Lobata",
        "city": "Guadalupe",
        "hamlet": "Quilombo Guadalupe",
        "municipality": "Guadalupe",
        "district": "Praia Plancas",
        "street": "EN1",
        "iso3166_2": "ST-05",
        "lon": 6.6109438,
        "lat": 0.4067896,
        "formatted": "Lagoa Azul, EN1, Guadalupe, São Tomé and Príncipe",
        "address_line1": "Lagoa Azul",
        "address_line2": "EN1, Guadalupe, São Tomé and Príncipe",
        "categories": [
          "tourism",
          "tourism.attraction",
          "tourism.attraction.viewpoint"
        ],
        "details": [],
        "datasource": {
          "sourcename": "openstreetmap",
          "attribution": "© OpenStreetMap contributors",
          "license": "Open Database License",
          "url": "https://www.openstreetmap.org/copyright",
          "raw": {
            "name": "Lagoa Azul",
            "osm_id": 2323324374,
            "tourism": "viewpoint",
            "osm_type": "n"
          }
        },
        "place_id": "519fc662409b711a405997f50a3fd708da3ff00103f901d61d7b8a0000000092030a4c61676f6120417a756c"
      },
      "geometry": {
        "type": "Point",
        "coordinates": [
          6.6109438,
          0.40678959995769887
        ]
      }
    },
    {
      "type": "Feature",
      "properties": {
        "name": "Praia Sete Ondas",
        "country": "São Tomé and Príncipe",
        "country_code": "st",
        "county": "Cantagalo",
        "city": "Ribeira Afonso",
        "hamlet": "Alto Douro",
        "municipality": "Ribeira Afonso",
        "street": "EN 2",
        "iso3166_2": "ST-02",
        "lon": 6.7070073,
        "lat": 0.2023069,
        "formatted": "Praia Sete Ondas, EN 2, Ribeira Afonso, São Tomé and Príncipe",
        "address_line1": "Praia Sete Ondas",
        "address_line2": "EN 2, Ribeira Afonso, São Tomé and Príncipe",
        "categories": [
          "tourism",
          "tourism.attraction",
          "tourism.attraction.viewpoint"
        ],
        "details": [],
        "datasource": {
          "sourcename": "openstreetmap",
          "attribution": "© OpenStreetMap contributors",
          "license": "Open Database License",
          "url": "https://www.openstreetmap.org/copyright",
          "raw": {
            "name": "Praia Sete Ondas",
            "osm_id": 2363005443,
            "tourism": "viewpoint",
            "osm_type": "n"
          }
        },
        "place_id": "510e22beb8f9d31a4059132b954731e5c93ff00103f901039ad88c0000000092031050726169612053657465204f6e646173"
      },
      "geometry": {
        "type": "Point",
        "coordinates": [
          6.707007299999999,
          0.20230689997909987
        ]
      }
    },
    {
      "type": "Feature",
      "properties": {
        "name": "Cascata de Bombaim",
        "country": "São Tomé and Príncipe",
        "country_code": "st",
        "county": "Mé-Zóchi",
        "city": "Monte Café",
        "hamlet": "Aldeamenta de Monta Café",
        "municipality": "Trindade",
        "street": "EN 3",
        "iso3166_2": "ST-06",
        "lon": 6.6300618,
        "lat": 0.2549912,
        "formatted": "Cascata de Bombaim, EN 3, Monte Café, São Tomé and Príncipe",
        "address_line1": "Cascata de Bombaim",
        "address_line2": "EN 3, Monte Café, São Tomé and Príncipe",
        "categories": [
          "tourism",
          "tourism.attraction"
        ],
        "details": [],
        "datasource": {
          "sourcename": "openstreetmap",
          "attribution": "© OpenStreetMap contributors",
          "license": "Open Database License",
          "url": "https://www.openstreetmap.org/copyright",
          "raw": {
            "name": "Cascata de Bombaim",
            "osm_id": 2401213448,
            "tourism": "attraction",
            "osm_type": "n",
            "waterway": "waterfall"
          }
        },
        "place_id": "51e8d5a5eb2e851a40595ee3299cc651d03ff00103f901089c1f8f000000009203124361736361746120646520426f6d6261696d"
      },
      "geometry": {
        "type": "Point",
        "coordinates": [
          6.6300618,
          0.25499119997362196
        ]
      }
    },
    {
      "type": "Feature",
      "properties": {
        "name": "Túnel",
        "country": "São Tomé and Príncipe",
        "country_code": "st",
        "county": "Lembá",
        "city": "Diogo Vaz",
        "hamlet": "Santa Clotilde",
        "municipality": "Neves",
        "street": "Túnel de Taiwan",
        "iso3166_2": "ST-04",
        "lon": 6.489827,
        "lat": 0.3090082,
        "formatted": "Túnel de Taiwan, Diogo Vaz, São Tomé and Príncipe",
        "address_line1": "Túnel de Taiwan",
        "address_line2": "Diogo Vaz, São Tomé and Príncipe",
        "categories": [
          "tourism",
          "tourism.attraction",
          "tourism.attraction.viewpoint"
        ],
        "details": [],
        "datasource": {
          "sourcename": "openstreetmap",
          "attribution": "© OpenStreetMap contributors",
          "license": "Open Database License",
          "url": "https://www.openstreetmap.org/copyright",
          "raw": {
            "name": "Túnel",
            "osm_id": 2401403659,
            "tourism": "viewpoint",
            "osm_type": "n"
          }
        },
        "place_id": "5189ca863595f5194059f4ba4354cac6d33ff00103f9010b83228f0000000092030654c3ba6e656c"
      },
      "geometry": {
        "type": "Point",
        "coordinates": [
          6.489826999999999,
          0.3090081999679761
        ]
      }
    },
    {
      "type": "Feature",
      "properties": {
        "name": "Boca do Inferno",
        "country": "São Tomé and Príncipe",
        "country_code": "st",
        "county": "Cantagalo",
        "city": "Ribeira Afonso",
        "hamlet": "Alto Douro",
        "municipality": "Ribeira Afonso",
        "street": "EN 2",
        "iso3166_2": "ST-02",
        "lon": 6.7262667,
        "lat": 0.2134475,
        "formatted": "Boca do Inferno, EN 2, Ribeira Afonso, São Tomé and Príncipe",
        "address_line1": "Boca do Inferno",
        "address_line2": "EN 2, Ribeira Afonso, São Tomé and Príncipe",
        "categories": [
          "tourism",
          "tourism.attraction",
          "tourism.attraction.viewpoint"
        ],
        "details": [],
        "datasource": {
          "sourcename": "openstreetmap",
          "attribution": "© OpenStreetMap contributors",
          "license": "Open Database License",
          "url": "https://www.openstreetmap.org/copyright",
          "raw": {
            "name": "Boca do Inferno",
            "osm_id": 2848219674,
            "tourism": "viewpoint",
            "osm_type": "n",
            "direction": 144
          }
        },
        "place_id": "5104b23275b2e71a4059f2bbe8673f52cb3ff00103f9011a62c4a90000000092030f426f636120646f20496e6665726e6f"
      },
      "geometry": {
        "type": "Point",
        "coordinates": [
          6.7262667,
          0.21344749997794527
        ]
      }
    },
    {
      "type": "Feature",
      "properties": {
        "name": "Cruce de Senderos",
        "country": "São Tomé and Príncipe",
        "country_code": "st",
        "county": "Lembá",
        "city": "Neves",
        "iso3166_2": "ST-04",
        "lon": 6.5454662,
        "lat": 0.2703757,
        "formatted": "Trail junction, Neves, Lembá, São Tomé and Príncipe",
        "address_line1": "Trail junction",
        "address_line2": "Neves, Lembá, São Tomé and Príncipe",
        "categories": [
          "tourism",
          "tourism.attraction"
        ],
        "details": [
          "details"
        ],
        "datasource": {
          "sourcename": "openstreetmap",
          "attribution": "© OpenStreetMap contributors",
          "license": "Open Database License",
          "url": "https://www.openstreetmap.org/copyright",
          "raw": {
            "name": "Cruce de Senderos",
            "osm_id": 5685124524,
            "name:en": "Trail junction",
            "name:es": "Cruce de Senderos",
            "tourism": "attraction",
            "osm_type": "n"
          }
        },
        "name_international": {
          "en": "Trail junction",
          "es": "Cruce de Senderos"
        },
        "place_id": "51274b08b18e2e1a405954d340e1d54dd13ff00103f901ac1ddc520100000092031143727563652064652053656e6465726f73"
      },
      "geometry": {
        "type": "Point",
        "coordinates": [
          6.545466199999999,
          0.2703756999720117
        ]
      }
    },
    {
      "type": "Feature",
      "properties": {
        "name": "Vista a Cascada Pesqueira",
        "country": "São Tomé and Príncipe",
        "country_code": "st",
        "county": "Caué",
        "city": "Ribeira Peixe",
        "hamlet": "Praia Pesqueira",
        "municipality": "São João dos Angolares",
        "street": "EN 2",
        "iso3166_2": "ST-03",
        "lon": 6.6208803,
        "lat": 0.0984237,
        "formatted": "Vista a Cascada Pesqueira, EN 2, Ribeira Peixe, São Tomé and Príncipe",
        "address_line1": "Vista a Cascada Pesqueira",
        "address_line2": "EN 2, Ribeira Peixe, São Tomé and Príncipe",
        "categories": [
          "tourism",
          "tourism.attraction",
          "tourism.attraction.viewpoint"
        ],
        "details": [
          "details"
        ],
        "datasource": {
          "sourcename": "openstreetmap",
          "attribution": "© OpenStreetMap contributors",
          "license": "Open Database License",
          "url": "https://www.openstreetmap.org/copyright",
          "raw": {
            "name": "Vista a Cascada Pesqueira",
            "osm_id": 6805500685,
            "name:es": "Vista a Cascada Pesqueira",
            "tourism": "viewpoint",
            "osm_type": "n"
          }
        },
        "name_international": {
          "es": "Vista a Cascada Pesqueira"
        },
        "place_id": "5134ec9c0bc87b1a405948979bac4b32b93ff00103f9010db3a3950100000092031956697374612061204361736361646120506573717565697261"
      },
      "geometry": {
        "type": "Point",
        "coordinates": [
          6.6208803,
          0.098423699989863
        ]
      }
    },
    {
      "type": "Feature",
      "properties": {
        "name": "Cascata de Praia Pesqueira",
        "country": "São Tomé and Príncipe",
        "country_code": "st",
        "county": "Caué",
        "city": "Ribeira Peixe",
        "hamlet": "Praia Pesqueira",
        "municipality": "São João dos Angolares",
        "street": "EN 2",
        "iso3166_2": "ST-03",
        "lon": 6.6204857,
        "lat": 0.0988531,
        "formatted": "Cascata de Praia Pesqueira, EN 2, Ribeira Peixe, São Tomé and Príncipe",
        "address_line1": "Cascata de Praia Pesqueira",
        "address_line2": "EN 2, Ribeira Peixe, São Tomé and Príncipe",
        "categories": [
          "tourism",
          "tourism.attraction",
          "tourism.attraction.viewpoint"
        ],
        "details": [
          "details"
        ],
        "datasource": {
          "sourcename": "openstreetmap",
          "attribution": "© OpenStreetMap contributors",
          "license": "Open Database License",
          "url": "https://www.openstreetmap.org/copyright",
          "raw": {
            "name": "Cascata de Praia Pesqueira",
            "osm_id": 9322943126,
            "name:es": "Cascada de la Playa Pesqueira",
            "name:pt": "Cascata de Praia Pesqueira",
            "tourism": "viewpoint",
            "osm_type": "n",
            "waterway": "waterfall"
          }
        },
        "name_international": {
          "es": "Cascada de la Playa Pesqueira",
          "pt": "Cascata de Praia Pesqueira"
        },
        "place_id": "51ec8a749a607b1a4059718690cf6f4eb93ff00103f90196d2b02b0200000092031a4361736361746120646520507261696120506573717565697261"
      },
      "geometry": {
        "type": "Point",
        "coordinates": [
          6.6204857,
          0.09885309998983317
        ]
      }
    },
    {
      "type": "Feature",
      "properties": {
        "name": "Paseo en Bote por los Manglares",
        "country": "São Tomé and Príncipe",
        "country_code": "st",
        "county": "Caué",
        "city": "Porto Alegre",
        "municipality": "Malanza",
        "street": "EN 2",
        "iso3166_2": "ST-03",
        "lon": 6.5322268,
        "lat": 0.0447953,
        "formatted": "Mangrove Boat Tour, EN 2, Porto Alegre, São Tomé and Príncipe",
        "address_line1": "Mangrove Boat Tour",
        "address_line2": "EN 2, Porto Alegre, São Tomé and Príncipe",
        "categories": [
          "tourism",
          "tourism.attraction"
        ],
        "details": [
          "details"
        ],
        "datasource": {
          "sourcename": "openstreetmap",
          "attribution": "© OpenStreetMap contributors",
          "license": "Open Database License",
          "url": "https://www.openstreetmap.org/copyright",
          "raw": {
            "name": "Paseo en Bote por los Manglares",
            "osm_id": 9983545417,
            "name:en": "Mangrove Boat Tour",
            "name:es": "Paseo en Bote por los Manglares",
            "tourism": "attraction",
            "osm_type": "n"
          }
        },
        "name_international": {
          "en": "Mangrove Boat Tour",
          "es": "Paseo en Bote por los Manglares"
        },
        "place_id": "510b38f00f00211a4059ea49fdd868efa63ff00103f90149d010530200000092031f506173656f20656e20426f746520706f72206c6f73204d616e676c61726573"
      },
      "geometry": {
        "type": "Point",
        "coordinates": [
          6.532226799999999,
          0.04479529999538896
        ]
      }
    },
    {
      "type": "Feature",
      "properties": {
        "name": "Ilhéu de Santana",
        "country": "São Tomé and Príncipe",
        "country_code": "st",
        "county": "Cantagalo",
        "city": "Riboque Santana",
        "hamlet": "Picao Flor",
        "municipality": "Santana",
        "street": "EN 2",
        "iso3166_2": "ST-02",
        "lon": 6.7593701,
        "lat": 0.2413807,
        "formatted": "Ilhéu de Santana, EN 2, Riboque Santana, São Tomé and Príncipe",
        "address_line1": "Ilhéu de Santana",
        "address_line2": "EN 2, Riboque Santana, São Tomé and Príncipe",
        "categories": [
          "tourism",
          "tourism.attraction"
        ],
        "details": [],
        "datasource": {
          "sourcename": "openstreetmap",
          "attribution": "© OpenStreetMap contributors",
          "license": "Open Database License",
          "url": "https://www.openstreetmap.org/copyright",
          "raw": {
            "name": "Ilhéu de Santana",
            "osm_id": 11438155069,
            "tourism": "attraction",
            "osm_type": "n"
          }
        },
        "place_id": "51b13dc45098091b405927a1231290e5ce3ff00103f9013d65c4a902000000920311496c68c3a9752064652053616e74616e61"
      },
      "geometry": {
        "type": "Point",
        "coordinates": [
          6.759370099999999,
          0.24138069997503317
        ]
      }
    },
    {
      "type": "Feature",
      "properties": {
        "name": "Boca do Inferno",
        "country": "São Tomé and Príncipe",
        "country_code": "st",
        "county": "Cantagalo",
        "city": "Ribeira Afonso",
        "hamlet": "Alto Douro",
        "municipality": "Ribeira Afonso",
        "street": "EN 2",
        "iso3166_2": "ST-02",
        "lon": 6.7263349,
        "lat": 0.2133066,
        "formatted": "Boca do Inferno, EN 2, Ribeira Afonso, São Tomé and Príncipe",
        "address_line1": "Boca do Inferno",
        "address_line2": "EN 2, Ribeira Afonso, São Tomé and Príncipe",
        "categories": [
          "tourism",
          "tourism.attraction"
        ],
        "details": [],
        "datasource": {
          "sourcename": "openstreetmap",
          "attribution": "© OpenStreetMap contributors",
          "license": "Open Database License",
          "url": "https://www.openstreetmap.org/copyright",
          "raw": {
            "name": "Boca do Inferno",
            "osm_id": 11966081199,
            "tourism": "attraction",
            "osm_type": "n"
          }
        },
        "place_id": "5112c60556c4e71a40597c907673a14dcb3ff00103f901afe83bc90200000092030f426f636120646f20496e6665726e6f"
      },
      "geometry": {
        "type": "Point",
        "coordinates": [
          6.7263348999999995,
          0.2133065999779581
        ]
      }
    },
    {
      "type": "Feature",
      "properties": {
        "country": "São Tomé and Príncipe",
        "country_code": "st",
        "county": "Caué",
        "city": "Porto Alegre",
        "municipality": "Malanza",
        "street": "EN 2",
        "iso3166_2": "ST-03",
        "lon": 6.521368,
        "lat": -0.0121206,
        "formatted": "EN 2, Porto Alegre, São Tomé and Príncipe",
        "address_line1": "EN 2",
        "address_line2": "Porto Alegre, São Tomé and Príncipe",
        "categories": [
          "tourism",
          "tourism.attraction",
          "tourism.attraction.viewpoint"
        ],
        "details": [],
        "datasource": {
          "sourcename": "openstreetmap",
          "attribution": "© OpenStreetMap contributors",
          "license": "Open Database License",
          "url": "https://www.openstreetmap.org/copyright",
          "raw": {
            "osm_id": 2177385324,
            "tourism": "viewpoint",
            "osm_type": "n"
          }
        },
        "place_id": "5144b9347ee1151a40598219d264afd288bff00103f9016c43c88100000000"
      },
      "geometry": {
        "type": "Point",
        "coordinates": [
          6.521367999999999,
          -0.012120599998763696
        ]
      }
    },
    {
      "type": "Feature",
      "properties": {
        "country": "São Tomé and Príncipe",
        "country_code": "st",
        "county": "Mé-Zóchi",
        "city": "Monte Café",
        "hamlet": "Aldeamenta de Monta Café",
        "municipality": "Trindade",
        "street": "EN 3",
        "iso3166_2": "ST-06",
        "lon": 6.5920352,
        "lat": 0.2807866,
        "formatted": "EN 3, Monte Café, São Tomé and Príncipe",
        "address_line1": "EN 3",
        "address_line2": "Monte Café, São Tomé and Príncipe",
        "categories": [
          "tourism",
          "tourism.attraction",
          "tourism.attraction.viewpoint"
        ],
        "details": [],
        "datasource": {
          "sourcename": "openstreetmap",
          "attribution": "© OpenStreetMap contributors",
          "license": "Open Database License",
          "url": "https://www.openstreetmap.org/copyright",
          "raw": {
            "osm_id": 2401392111,
            "tourism": "viewpoint",
            "osm_type": "n"
          }
        },
        "place_id": "51c152b8793e5e1a405958ee015c68f8d13ff00103f901ef55228f00000000"
      },
      "geometry": {
        "type": "Point",
        "coordinates": [
          6.592035199999999,
          0.2807865999709285
        ]
      }
    },
    {
      "type": "Feature",
      "properties": {
        "country": "São Tomé and Príncipe",
        "country_code": "st",
        "county": "Caué",
        "city": "São João dos Angolares",
        "hamlet": "São João",
        "municipality": "São João dos Angolares",
        "street": "EN 2",
        "iso3166_2": "ST-03",
        "lon": 6.6463536,
        "lat": 0.1319031,
        "formatted": "EN 2, São João dos Angolares, São Tomé and Príncipe",
        "address_line1": "EN 2",
        "address_line2": "São João dos Angolares, São Tomé and Príncipe",
        "categories": [
          "tourism",
          "tourism.attraction",
          "tourism.attraction.viewpoint"
        ],
        "details": [],
        "datasource": {
          "sourcename": "openstreetmap",
          "attribution": "© OpenStreetMap contributors",
          "license": "Open Database License",
          "url": "https://www.openstreetmap.org/copyright",
          "raw": {
            "osm_id": 2848220604,
            "tourism": "viewpoint",
            "osm_type": "n"
          }
        },
        "place_id": "51829bd6b7dd951a4059c560576633e2c03ff00103f901bc65c4a900000000"
      },
      "geometry": {
        "type": "Point",
        "coordinates": [
          6.646353599999999,
          0.13190309998640806
        ]
      }
    },
    {
      "type": "Feature",
      "properties": {
        "country": "São Tomé and Príncipe",
        "country_code": "st",
        "county": "Caué",
        "city": "Porto Alegre",
        "municipality": "Malanza",
        "street": "EN 2",
        "iso3166_2": "ST-03",
        "lon": 6.5190668,
        "lat": 4.29e-05,
        "formatted": "EN 2, Porto Alegre, São Tomé and Príncipe",
        "address_line1": "EN 2",
        "address_line2": "Porto Alegre, São Tomé and Príncipe",
        "categories": [
          "tourism",
          "tourism.attraction",
          "tourism.attraction.viewpoint"
        ],
        "details": [],
        "datasource": {
          "sourcename": "openstreetmap",
          "attribution": "© OpenStreetMap contributors",
          "license": "Open Database License",
          "url": "https://www.openstreetmap.org/copyright",
          "raw": {
            "osm_id": 3019345259,
            "tourism": "viewpoint",
            "osm_type": "n"
          }
        },
        "place_id": "51eac1493f86131a4059c4b899c6f07d063ff00103f9016b8df7b300000000"
      },
      "geometry": {
        "type": "Point",
        "coordinates": [
          6.519066799999999,
          4.289999999406013e-05
        ]
      }
    },
    {
      "type": "Feature",
      "properties": {
        "country": "São Tomé and Príncipe",
        "country_code": "st",
        "county": "Água Grande",
        "city": "São Tomé",
        "hamlet": "São Gabriel",
        "street": "Estrada de Pantufo",
        "iso3166_2": "ST-01",
        "lon": 6.7423034,
        "lat": 0.3330087,
        "formatted": "Estrada de Pantufo, São Tomé, São Tomé and Príncipe",
        "address_line1": "Estrada de Pantufo",
        "address_line2": "São Tomé, São Tomé and Príncipe",
        "categories": [
          "tourism",
          "tourism.attraction",
          "tourism.attraction.viewpoint"
        ],
        "details": [],
        "datasource": {
          "sourcename": "openstreetmap",
          "attribution": "© OpenStreetMap contributors",
          "license": "Open Database License",
          "url": "https://www.openstreetmap.org/copyright",
          "raw": {
            "osm_id": 4473972807,
            "tourism": "viewpoint",
            "osm_type": "n"
          }
        },
        "place_id": "51a3d6ea611ef81a4059eea5e8b80350d53ff00103f9014768ab0a01000000"
      },
      "geometry": {
        "type": "Point",
        "coordinates": [
          6.7423034,
          0.3330086999654601
        ]
      }
    },
    {
      "type": "Feature",
      "properties": {
        "name": "Equatorial line according to GPS",
        "country": "São Tomé and Príncipe",
        "country_code": "st",
        "county": "Caué",
        "city": "Porto Alegre",
        "municipality": "Malanza",
        "street": "EN 2",
        "iso3166_2": "ST-03",
        "lon": 6.5238675,
        "lat": 0.0001199,
        "formatted": "Equatorial line according to GPS, EN 2, Porto Alegre, São Tomé and Príncipe",
        "address_line1": "Equatorial line according to GPS",
        "address_line2": "EN 2, Porto Alegre, São Tomé and Príncipe",
        "categories": [
          "tourism",
          "tourism.attraction"
        ],
        "details": [
          "details"
        ],
        "datasource": {
          "sourcename": "openstreetmap",
          "attribution": "© OpenStreetMap contributors",
          "license": "Open Database License",
          "url": "https://www.openstreetmap.org/copyright",
          "raw": {
            "osm_id": 6810319585,
            "name:en": "Equatorial line according to GPS",
            "name:es": "Linea de ecuador según GPS",
            "tourism": "attraction",
            "osm_type": "n"
          }
        },
        "name_international": {
          "en": "Equatorial line according to GPS",
          "es": "Linea de ecuador según GPS"
        },
        "place_id": "51c6bfcfb870181a40590f6f98505a6e1f3ff00103f901e13aed9501000000"
      },
      "geometry": {
        "type": "Point",
        "coordinates": [
          6.5238675,
          0.00011989999998046292
        ]
      }
    },
    {
      "type": "Feature",
      "properties": {
        "country": "São Tomé and Príncipe",
        "country_code": "st",
        "county": "Água Grande",
        "city": "São Tomé",
        "hamlet": "Lucumi",
        "street": "Rua Moçambique",
        "iso3166_2": "ST-01",
        "lon": 6.7305638,
        "lat": 0.3394252,
        "formatted": "Rua Moçambique, São Tomé, São Tomé and Príncipe",
        "address_line1": "Rua Moçambique",
        "address_line2": "São Tomé, São Tomé and Príncipe",
        "categories": [
          "tourism",
          "tourism.attraction",
          "tourism.attraction.artwork"
        ],
        "details": [
          "details.artwork"
        ],
        "datasource": {
          "sourcename": "openstreetmap",
          "attribution": "© OpenStreetMap contributors",
          "license": "Open Database License",
          "url": "https://www.openstreetmap.org/copyright",
          "raw": {
            "osm_id": 10304698349,
            "tourism": "artwork",
            "material": "metal",
            "osm_type": "n",
            "artwork_type": "sculpture"
          }
        },
        "artwork": {
          "artwork_type": "sculpture"
        },
        "place_id": "51e090b2ea18ec1a4059a95e527924b9d53ff00103f901ed37356602000000"
      },
      "geometry": {
        "type": "Point",
        "coordinates": [
          6.730563799999999,
          0.33942519996478865
        ]
      }
    },
    {
      "type": "Feature",
      "properties": {
        "country": "São Tomé and Príncipe",
        "country_code": "st",
        "county": "Água Grande",
        "city": "São Tomé",
        "hamlet": "Ponta Mina",
        "street": "Avenida Marginal 12 Julho",
        "iso3166_2": "ST-01",
        "lon": 6.732977,
        "lat": 0.3395936,
        "formatted": "Avenida Marginal 12 Julho, São Tomé, São Tomé and Príncipe",
        "address_line1": "Avenida Marginal 12 Julho",
        "address_line2": "São Tomé, São Tomé and Príncipe",
        "categories": [
          "tourism",
          "tourism.attraction",
          "tourism.attraction.artwork"
        ],
        "details": [
          "details.artwork"
        ],
        "datasource": {
          "sourcename": "openstreetmap",
          "attribution": "© OpenStreetMap contributors",
          "license": "Open Database License",
          "url": "https://www.openstreetmap.org/copyright",
          "raw": {
            "osm_id": 10304698403,
            "tourism": "artwork",
            "material": "metal",
            "osm_type": "n",
            "artwork_type": "installation"
          }
        },
        "artwork": {
          "artwork_type": "installation"
        },
        "place_id": "517ae1ce8591ee1a4059dee471cbe6bbd53ff00103f9012338356602000000"
      },
      "geometry": {
        "type": "Point",
        "coordinates": [
          6.732977,
          0.33959359996477
        ]
      }
    },
    {
      "type": "Feature",
      "properties": {
        "country": "São Tomé and Príncipe",
        "country_code": "st",
        "county": "Água Grande",
        "city": "São Tomé",
        "hamlet": "Ponta Mina",
        "street": "Avenida das Nações Unidas",
        "iso3166_2": "ST-01",
        "lon": 6.7381835,
        "lat": 0.3366537,
        "formatted": "Avenida das Nações Unidas, São Tomé, São Tomé and Príncipe",
        "address_line1": "Avenida das Nações Unidas",
        "address_line2": "São Tomé, São Tomé and Príncipe",
        "categories": [
          "tourism",
          "tourism.attraction",
          "tourism.attraction.artwork"
        ],
        "details": [
          "details.artwork"
        ],
        "datasource": {
          "sourcename": "openstreetmap",
          "attribution": "© OpenStreetMap contributors",
          "license": "Open Database License",
          "url": "https://www.openstreetmap.org/copyright",
          "raw": {
            "osm_id": 10305101162,
            "tourism": "artwork",
            "osm_type": "n",
            "artwork_type": "sculpture"
          }
        },
        "artwork": {
          "artwork_type": "sculpture"
        },
        "place_id": "518ac91b60e6f31a4059865adbf5bb8bd53ff00103f9016a5d3b6602000000"
      },
      "geometry": {
        "type": "Point",
        "coordinates": [
          6.7381835,
          0.33665369996507655
        ]
      }
    },
    {
      "type": "Feature",
      "properties": {
        "country": "São Tomé and Príncipe",
        "country_code": "st",
        "county": "Água Grande",
        "city": "São Tomé",
        "hamlet": "Ponta Mina",
        "street": "Praça da UCCLA",
        "iso3166_2": "ST-01",
        "lon": 6.7353867,
        "lat": 0.341217,
        "formatted": "Praça da UCCLA, São Tomé, São Tomé and Príncipe",
        "address_line1": "Praça da UCCLA",
        "address_line2": "São Tomé, São Tomé and Príncipe",
        "categories": [
          "tourism",
          "tourism.attraction",
          "tourism.attraction.artwork"
        ],
        "details": [
          "details.artwork"
        ],
        "datasource": {
          "sourcename": "openstreetmap",
          "attribution": "© OpenStreetMap contributors",
          "license": "Open Database License",
          "url": "https://www.openstreetmap.org/copyright",
          "raw": {
            "osm_id": 10311218598,
            "tourism": "artwork",
            "osm_type": "n",
            "artwork_type": "sculpture"
          }
        },
        "artwork": {
          "artwork_type": "sculpture"
        },
        "place_id": "5148a7093609f11a405920faebd37fd6d53ff00103f901a6b5986602000000"
      },
      "geometry": {
        "type": "Point",
        "coordinates": [
          6.735386699999999,
          0.34121699996458865
        ]
      }
    },
    {
      "type": "Feature",
      "properties": {
        "country": "São Tomé and Príncipe",
        "country_code": "st",
        "county": "Água Grande",
        "city": "São Tomé",
        "hamlet": "Ponta Mina",
        "street": "Praça da UCCLA",
        "iso3166_2": "ST-01",
        "lon": 6.7353642,
        "lat": 0.3411678,
        "formatted": "Praça da UCCLA, São Tomé, São Tomé and Príncipe",
        "address_line1": "Praça da UCCLA",
        "address_line2": "São Tomé, São Tomé and Príncipe",
        "categories": [
          "tourism",
          "tourism.attraction",
          "tourism.attraction.artwork"
        ],
        "details": [
          "details.artwork"
        ],
        "datasource": {
          "sourcename": "openstreetmap",
          "attribution": "© OpenStreetMap contributors",
          "license": "Open Database License",
          "url": "https://www.openstreetmap.org/copyright",
          "raw": {
            "osm_id": 10311218599,
            "tourism": "artwork",
            "osm_type": "n",
            "artwork_type": "sculpture"
          }
        },
        "artwork": {
          "artwork_type": "sculpture"
        },
        "place_id": "51c998165003f11a405994f5d277b1d5d53ff00103f901a7b5986602000000"
      },
      "geometry": {
        "type": "Point",
        "coordinates": [
          6.7353642,
          0.3411677999646028
        ]
      }
    },
    {
      "type": "Feature",
      "properties": {
        "country": "São Tomé and Príncipe",
        "country_code": "st",
        "county": "Água Grande",
        "city": "São Tomé",
        "hamlet": "Ponta Mina",
        "street": "Praça da UCCLA",
        "iso3166_2": "ST-01",
        "lon": 6.7353417,
        "lat": 0.3411186,
        "formatted": "Praça da UCCLA, São Tomé, São Tomé and Príncipe",
        "address_line1": "Praça da UCCLA",
        "address_line2": "São Tomé, São Tomé and Príncipe",
        "categories": [
          "tourism",
          "tourism.attraction",
          "tourism.attraction.artwork"
        ],
        "details": [
          "details.artwork"
        ],
        "datasource": {
          "sourcename": "openstreetmap",
          "attribution": "© OpenStreetMap contributors",
          "license": "Open Database License",
          "url": "https://www.openstreetmap.org/copyright",
          "raw": {
            "osm_id": 10311218600,
            "tourism": "artwork",
            "osm_type": "n",
            "artwork_type": "sculpture"
          }
        },
        "artwork": {
          "artwork_type": "sculpture"
        },
        "place_id": "51498a236afdf01a405922f0b91be3d4d53ff00103f901a8b5986602000000"
      },
      "geometry": {
        "type": "Point",
        "coordinates": [
          6.7353417,
          0.34111859996460414
        ]
      }
    },
    {
      "type": "Feature",
      "properties": {
        "country": "São Tomé and Príncipe",
        "country_code": "st",
        "county": "Água Grande",
        "city": "São Tomé",
        "suburb": "Riboque",
        "street": "Avenida Marginal 12 Julho",
        "iso3166_2": "ST-01",
        "lon": 6.7371891,
        "lat": 0.3450746,
        "formatted": "Avenida Marginal 12 Julho, São Tomé, São Tomé and Príncipe",
        "address_line1": "Avenida Marginal 12 Julho",
        "address_line2": "São Tomé, São Tomé and Príncipe",
        "categories": [
          "tourism",
          "tourism.attraction",
          "tourism.attraction.artwork"
        ],
        "details": [
          "details.artwork"
        ],
        "datasource": {
          "sourcename": "openstreetmap",
          "attribution": "© OpenStreetMap contributors",
          "license": "Open Database License",
          "url": "https://www.openstreetmap.org/copyright",
          "raw": {
            "osm_id": 10312836940,
            "tourism": "artwork",
            "osm_type": "n",
            "artwork_type": "sculpture"
          }
        },
        "artwork": {
          "artwork_type": "sculpture"
        },
        "place_id": "51e6de0db3e1f21a4059e2b161c6b315d63ff00103f9014c67b16602000000"
      },
      "geometry": {
        "type": "Point",
        "coordinates": [
          6.7371891,
          0.34507459996419076
        ]
      }
    },
    {
      "type": "Feature",
      "properties": {
        "name": "Pico Grande",
        "country": "São Tomé and Príncipe",
        "country_code": "st",
        "county": "Caué",
        "city": "Ribeira Peixe",
        "hamlet": "Praia Pesqueira",
        "municipality": "São João dos Angolares",
        "district": "Vila Aida",
        "street": "EN 2",
        "iso3166_2": "ST-03",
        "lon": 6.5810286,
        "lat": 0.0928287,
        "formatted": "Pico Grande, EN 2, Ribeira Peixe, São Tomé and Príncipe",
        "address_line1": "Pico Grande",
        "address_line2": "EN 2, Ribeira Peixe, São Tomé and Príncipe",
        "categories": [
          "tourism",
          "tourism.attraction",
          "tourism.attraction.viewpoint"
        ],
        "details": [
          "details"
        ],
        "datasource": {
          "sourcename": "openstreetmap",
          "attribution": "© OpenStreetMap contributors",
          "license": "Open Database License",
          "url": "https://www.openstreetmap.org/copyright",
          "raw": {
            "osm_id": 11534765969,
            "name:en": "Pico Grande",
            "tourism": "viewpoint",
            "osm_type": "n"
          }
        },
        "name_international": {
          "en": "Pico Grande"
        },
        "place_id": "51a3294c29f9521a405940d496269fc3b73ff00103f901918f86af02000000"
      },
      "geometry": {
        "type": "Point",
        "coordinates": [
          6.581028599999999,
          0.09282869999044951
        ]
      }
    },
    {
      "type": "Feature",
      "properties": {
        "name": "Abandoned house",
        "country": "São Tomé and Príncipe",
        "country_code": "st",
        "county": "Cantagalo",
        "city": "Colonia Acoreana",
        "hamlet": "Santa Cecilia",
        "municipality": "Ribeira Afonso",
        "district": "Cavalete",
        "street": "EN 2",
        "iso3166_2": "ST-02",
        "lon": 6.6822894,
        "lat": 0.1780395,
        "formatted": "Abandoned house, EN 2, Colonia Acoreana, São Tomé and Príncipe",
        "address_line1": "Abandoned house",
        "address_line2": "EN 2, Colonia Acoreana, São Tomé and Príncipe",
        "categories": [
          "tourism",
          "tourism.attraction"
        ],
        "details": [
          "details"
        ],
        "datasource": {
          "sourcename": "openstreetmap",
          "attribution": "© OpenStreetMap contributors",
          "license": "Open Database License",
          "url": "https://www.openstreetmap.org/copyright",
          "raw": {
            "osm_id": 11534766069,
            "name:en": "Abandoned house",
            "tourism": "attraction",
            "osm_type": "n"
          }
        },
        "name_international": {
          "en": "Abandoned house"
        },
        "place_id": "513ea18d12aaba1a40599a9ce892ffc9c63ff00103f901f58f86af02000000"
      },
      "geometry": {
        "type": "Point",
        "coordinates": [
          6.6822894,
          0.17803949998162666
        ]
      }
    },
    {
      "type": "Feature",
      "properties": {
        "name": "Abandoned hospital",
        "country": "São Tomé and Príncipe",
        "country_code": "st",
        "county": "Cantagalo",
        "city": "Ribeira Afonso",
        "hamlet": "Alto Douro",
        "municipality": "Ribeira Afonso",
        "street": "EN 2",
        "iso3166_2": "ST-02",
        "lon": 6.7248579,
        "lat": 0.2178597,
        "formatted": "Abandoned hospital, EN 2, Ribeira Afonso, São Tomé and Príncipe",
        "address_line1": "Abandoned hospital",
        "address_line2": "EN 2, Ribeira Afonso, São Tomé and Príncipe",
        "categories": [
          "tourism",
          "tourism.attraction"
        ],
        "details": [
          "details"
        ],
        "datasource": {
          "sourcename": "openstreetmap",
          "attribution": "© OpenStreetMap contributors",
          "license": "Open Database License",
          "url": "https://www.openstreetmap.org/copyright",
          "raw": {
            "osm_id": 11534766169,
            "name:en": "Abandoned hospital",
            "tourism": "attraction",
            "osm_type": "n"
          }
        },
        "name_international": {
          "en": "Abandoned hospital"
        },
        "place_id": "512dfd3a2641e61a4059ab84429fd3e2cb3ff00103f901599086af02000000"
      },
      "geometry": {
        "type": "Point",
        "coordinates": [
          6.724857900000001,
          0.21785969997748586
        ]
      }
    },
    {
      "type": "Feature",
      "properties": {
        "name": "Equatorial line according to GPS",
        "country": "São Tomé and Príncipe",
        "country_code": "st",
        "county": "Caué",
        "city": "Porto Alegre",
        "municipality": "Malanza",
        "street": "EN 2",
        "iso3166_2": "ST-03",
        "lon": 6.518987,
        "lat": 7e-07,
        "formatted": "Equatorial line according to GPS, EN 2, Porto Alegre, São Tomé and Príncipe",
        "address_line1": "Equatorial line according to GPS",
        "address_line2": "EN 2, Porto Alegre, São Tomé and Príncipe",
        "categories": [
          "tourism",
          "tourism.attraction"
        ],
        "details": [
          "details"
        ],
        "datasource": {
          "sourcename": "openstreetmap",
          "attribution": "© OpenStreetMap contributors",
          "license": "Open Database License",
          "url": "https://www.openstreetmap.org/copyright",
          "raw": {
            "osm_id": 12090372443,
            "name:en": "Equatorial line according to GPS",
            "name:es": "Linea de ecuador según GPS",
            "tourism": "attraction",
            "osm_type": "n"
          }
        },
        "name_international": {
          "en": "Equatorial line according to GPS",
          "es": "Linea de ecuador según GPS"
        },
        "place_id": "515532005471131a405972981646f47ca73ef00103f9015b71a4d002000000"
      },
      "geometry": {
        "type": "Point",
        "coordinates": [
          6.518987,
          6.999999976789149e-07
        ]
      }
    }
  ]
}